rotaeno_stablizer-1.0.0.dist-info/METADATA
rotaeno_stablizer-1.0.0.dist-info/WHEEL
rotaeno_stablizer-1.0.0.dist-info/entry_points.txt
rotaeno_stablizer-1.0.0.dist-info/licenses/LICENSE
rotaeno_stablizer/__init__.py
rotaeno_stablizer/__main__.py
rotaeno_stablizer/background.py
rotaeno_stablizer/cli.py
rotaeno_stablizer/config.py
rotaeno_stablizer/ffmpeg.py
rotaeno_stablizer/gui.py
rotaeno_stablizer/log.py
rotaeno_stablizer/logo.png
rotaeno_stablizer/rotaeno_logo_black.png
rotaeno_stablizer/rotation_calc.py
rotaeno_stablizer/utils.py
rotaeno_stablizer-1.0.0.dist-info/RECORD
