Metadata-Version: 2.4
Name: rotaeno-stablizer
Version: 1.0.0
Summary: Default template for PDM package
Author-Email: I Love Study <ilstudy@qq.com>
License-Expression: LGPL-3.0-or-later
Requires-Python: >=3.10
Requires-Dist: rich>=13.7.1
Requires-Dist: rich-argparse>=1.4.0
Requires-Dist: pillow>=11.0.0
Requires-Dist: rtoml>=0.11.0; python_version < "3.11"
Provides-Extra: gui
Requires-Dist: customtkinter>=5.2.2; extra == "gui"
Requires-Dist: CTkTable>=1.1; extra == "gui"
Requires-Dist: CTkMessagebox>=2.7; extra == "gui"
Requires-Dist: CTkMenuBar>=0.8; extra == "gui"
